mussel/__init__.py
mussel-1.1.0.dist-info/entry_points.txt
mussel-1.1.0.dist-info/LICENSE
mussel-1.1.0.dist-info/WHEEL
mussel-1.1.0.dist-info/METADATA
mussel-1.1.0.dist-info/RECORD
