Metadata-Version: 2.1
Name: mussel
Version: 1.1.0
Summary: Build Python executable for any environment with pyinstaller
License: MIT
Author: Thomas Mahé
Author-email: contact@tmahe.dev
Requires-Python: >=3.8,<4.0
Classifier: License :: OSI Approved :: MIT License
Classifier: Programming Language :: Python :: 3
Classifier: Programming Language :: Python :: 3.8
Classifier: Programming Language :: Python :: 3.9
Classifier: Programming Language :: Python :: 3.10
Classifier: Programming Language :: Python :: 3.11
